{"traceEvents":[{"pid":1,"tid":0,"ph":"X","ts":2548,"dur":725,"name":"Source","args":{"detail":"/usr/include/features.h"}},{"pid":1,"tid":0,"ph":"X","ts":2472,"dur":812,"name":"Source","args":{"detail":"/usr/bin/../lib/gcc/x86_64-linux-gnu/10/../../../../include/x86_64-linux-gnu/c++/10/bits/os_defines.h"}},{"pid":1,"tid":0,"ph":"X","ts":1950,"dur":1725,"name":"Source","args":{"detail":"/usr/bin/../lib/gcc/x86_64-linux-gnu/10/../../../../include/x86_64-linux-gnu/c++/10/bits/c++config.h"}},{"pid":1,"tid":0,"ph":"X","ts":3706,"dur":2881,"name":"Source","args":{"detail":"/usr/bin/../lib/gcc/x86_64-linux-gnu/10/../../../../include/c++/10/bits/cpp_type_traits.h"}},{"pid":1,"tid":0,"ph":"X","ts":6636,"dur":1590,"name":"Source","args":{"detail":"/usr/bin/../lib/gcc/x86_64-linux-gnu/10/../../../../include/c++/10/ext/type_traits.h"}},{"pid":1,"tid":0,"ph":"X","ts":8470,"dur":613,"name":"Source","args":{"detail":"/usr/include/x86_64-linux-gnu/bits/types.h"}},{"pid":1,"tid":0,"ph":"X","ts":10256,"dur":4949,"name":"Source","args":{"detail":"/usr/include/x86_64-linux-gnu/bits/mathcalls.h"}},{"pid":1,"tid":0,"ph":"X","ts":15422,"dur":5100,"name":"Source","args":{"detail":"/usr/include/x86_64-linux-gnu/bits/mathcalls.h"}},{"pid":1,"tid":0,"ph":"X","ts":20739,"dur":4904,"name":"Source","args":{"detail":"/usr/include/x86_64-linux-gnu/bits/mathcalls.h"}},{"pid":1,"tid":0,"ph":"X","ts":25675,"dur":4869,"name":"Source","args":{"detail":"/usr/include/x86_64-linux-gnu/bits/mathcalls.h"}},{"pid":1,"tid":0,"ph":"X","ts":30567,"dur":5462,"name":"Source","args":{"detail":"/usr/include/x86_64-linux-gnu/bits/mathcalls.h"}},{"pid":1,"tid":0,"ph":"X","ts":36070,"dur":4902,"name":"Source","args":{"detail":"/usr/include/x86_64-linux-gnu/bits/mathcalls.h"}},{"pid":1,"tid":0,"ph":"X","ts":40994,"dur":4675,"name":"Source","args":{"detail":"/usr/include/x86_64-linux-gnu/bits/mathcalls.h"}},{"pid":1,"tid":0,"ph":"X","ts":8286,"dur":40183,"name":"Source","args":{"detail":"/usr/include/math.h"}},{"pid":1,"tid":0,"ph":"X","ts":51717,"dur":675,"name":"Source","args":{"detail":"/usr/include/endian.h"}},{"pid":1,"tid":0,"ph":"X","ts":52570,"dur":638,"name":"Source","args":{"detail":"/usr/include/x86_64-linux-gnu/sys/select.h"}},{"pid":1,"tid":0,"ph":"X","ts":53334,"dur":632,"name":"Source","args":{"detail":"/usr/include/x86_64-linux-gnu/bits/thread-shared-types.h"}},{"pid":1,"tid":0,"ph":"X","ts":53300,"dur":1086,"name":"Source","args":{"detail":"/usr/include/x86_64-linux-gnu/bits/pthreadtypes.h"}},{"pid":1,"tid":0,"ph":"X","ts":51030,"dur":3360,"name":"Source","args":{"detail":"/usr/include/x86_64-linux-gnu/sys/types.h"}},{"pid":1,"tid":0,"ph":"X","ts":48578,"dur":9409,"name":"Source","args":{"detail":"/usr/include/stdlib.h"}},{"pid":1,"tid":0,"ph":"X","ts":48508,"dur":10116,"name":"Source","args":{"detail":"/usr/bin/../lib/gcc/x86_64-linux-gnu/10/../../../../include/c++/10/bits/std_abs.h"}},{"pid":1,"tid":0,"ph":"X","ts":1815,"dur":72806,"name":"Source","args":{"detail":"/usr/bin/../lib/gcc/x86_64-linux-gnu/10/../../../../include/c++/10/cmath"}},{"pid":1,"tid":0,"ph":"X","ts":74933,"dur":721,"name":"Source","args":{"detail":"/usr/bin/../lib/gcc/x86_64-linux-gnu/10/../../../../include/c++/10/bits/stringfwd.h"}},{"pid":1,"tid":0,"ph":"X","ts":75806,"dur":3857,"name":"Source","args":{"detail":"/usr/include/wchar.h"}},{"pid":1,"tid":0,"ph":"X","ts":75739,"dur":4718,"name":"Source","args":{"detail":"/usr/bin/../lib/gcc/x86_64-linux-gnu/10/../../../../include/c++/10/cwchar"}},{"pid":1,"tid":0,"ph":"X","ts":80520,"dur":543,"name":"ParseClass","args":{"detail":"std::fpos"}},{"pid":1,"tid":0,"ph":"X","ts":75689,"dur":5623,"name":"Source","args":{"detail":"/usr/bin/../lib/gcc/x86_64-linux-gnu/10/../../../../include/c++/10/bits/postypes.h"}},{"pid":1,"tid":0,"ph":"X","ts":74893,"dur":7200,"name":"Source","args":{"detail":"/usr/bin/../lib/gcc/x86_64-linux-gnu/10/../../../../include/c++/10/iosfwd"}},{"pid":1,"tid":0,"ph":"X","ts":83594,"dur":837,"name":"ParseClass","args":{"detail":"std::type_info"}},{"pid":1,"tid":0,"ph":"X","ts":83410,"dur":1369,"name":"Source","args":{"detail":"/usr/bin/../lib/gcc/x86_64-linux-gnu/10/../../../../include/c++/10/typeinfo"}},{"pid":1,"tid":0,"ph":"X","ts":84821,"dur":1065,"name":"Source","args":{"detail":"/usr/bin/../lib/gcc/x86_64-linux-gnu/10/../../../../include/c++/10/new"}},{"pid":1,"tid":0,"ph":"X","ts":86031,"dur":658,"name":"ParseClass","args":{"detail":"std::__exception_ptr::exception_ptr"}},{"pid":1,"tid":0,"ph":"X","ts":82919,"dur":4305,"name":"Source","args":{"detail":"/usr/bin/../lib/gcc/x86_64-linux-gnu/10/../../../../include/c++/10/bits/exception_ptr.h"}},{"pid":1,"tid":0,"ph":"X","ts":104200,"dur":534,"name":"ParseClass","args":{"detail":"std::__make_signed"}},{"pid":1,"tid":0,"ph":"X","ts":87458,"dur":26343,"name":"Source","args":{"detail":"/usr/bin/../lib/gcc/x86_64-linux-gnu/10/../../../../include/c++/10/type_traits"}},{"pid":1,"tid":0,"ph":"X","ts":87309,"dur":27551,"name":"Source","args":{"detail":"/usr/bin/../lib/gcc/x86_64-linux-gnu/10/../../../../include/c++/10/bits/move.h"}},{"pid":1,"tid":0,"ph":"X","ts":87264,"dur":28876,"name":"Source","args":{"detail":"/usr/bin/../lib/gcc/x86_64-linux-gnu/10/../../../../include/c++/10/bits/nested_exception.h"}},{"pid":1,"tid":0,"ph":"X","ts":82136,"dur":34008,"name":"Source","args":{"detail":"/usr/bin/../lib/gcc/x86_64-linux-gnu/10/../../../../include/c++/10/exception"}},{"pid":1,"tid":0,"ph":"X","ts":116750,"dur":987,"name":"Source","args":{"detail":"/usr/bin/../lib/gcc/x86_64-linux-gnu/10/../../../../include/c++/10/ext/numeric_traits.h"}},{"pid":1,"tid":0,"ph":"X","ts":118074,"dur":569,"name":"ParseClass","args":{"detail":"std::_PCC"}},{"pid":1,"tid":0,"ph":"X","ts":118943,"dur":2879,"name":"ParseClass","args":{"detail":"std::pair"}},{"pid":1,"tid":0,"ph":"X","ts":117778,"dur":5073,"name":"Source","args":{"detail":"/usr/bin/../lib/gcc/x86_64-linux-gnu/10/../../../../include/c++/10/bits/stl_pair.h"}},{"pid":1,"tid":0,"ph":"X","ts":122904,"dur":923,"name":"Source","args":{"detail":"/usr/bin/../lib/gcc/x86_64-linux-gnu/10/../../../../include/c++/10/bits/stl_iterator_base_types.h"}},{"pid":1,"tid":0,"ph":"X","ts":123865,"dur":960,"name":"Source","args":{"detail":"/usr/bin/../lib/gcc/x86_64-linux-gnu/10/../../../../include/c++/10/bits/stl_iterator_base_funcs.h"}},{"pid":1,"tid":0,"ph":"X","ts":124963,"dur":1303,"name":"Source","args":{"detail":"/usr/bin/../lib/gcc/x86_64-linux-gnu/10/../../../../include/c++/10/bits/ptr_traits.h"}},{"pid":1,"tid":0,"ph":"X","ts":126325,"dur":835,"name":"ParseClass","args":{"detail":"std::reverse_iterator"}},{"pid":1,"tid":0,"ph":"X","ts":129561,"dur":627,"name":"ParseClass","args":{"detail":"__gnu_cxx::__normal_iterator"}},{"pid":1,"tid":0,"ph":"X","ts":131369,"dur":725,"name":"ParseClass","args":{"detail":"std::move_iterator"}},{"pid":1,"tid":0,"ph":"X","ts":124917,"dur":8837,"name":"Source","args":{"detail":"/usr/bin/../lib/gcc/x86_64-linux-gnu/10/../../../../include/c++/10/bits/stl_iterator.h"}},{"pid":1,"tid":0,"ph":"X","ts":133950,"dur":3521,"name":"Source","args":{"detail":"/usr/bin/../lib/gcc/x86_64-linux-gnu/10/../../../../include/c++/10/bits/predefined_ops.h"}},{"pid":1,"tid":0,"ph":"X","ts":116301,"dur":32034,"name":"Source","args":{"detail":"/usr/bin/../lib/gcc/x86_64-linux-gnu/10/../../../../include/c++/10/bits/stl_algobase.h"}},{"pid":1,"tid":0,"ph":"X","ts":148591,"dur":554,"name":"ParseClass","args":{"detail":"__gnu_cxx::char_traits"}},{"pid":1,"tid":0,"ph":"X","ts":149985,"dur":1111,"name":"ParseClass","args":{"detail":"std::char_traits"}},{"pid":1,"tid":0,"ph":"X","ts":151120,"dur":1012,"name":"ParseClass","args":{"detail":"std::char_traits"}},{"pid":1,"tid":0,"ph":"X","ts":152340,"dur":574,"name":"Source","args":{"detail":"/usr/include/stdint.h"}},{"pid":1,"tid":0,"ph":"X","ts":152287,"dur":711,"name":"Source","args":{"detail":"/usr/lib/llvm-10/lib/clang/10.0.0/include/stdint.h"}},{"pid":1,"tid":0,"ph":"X","ts":152218,"dur":895,"name":"Source","args":{"detail":"/usr/bin/../lib/gcc/x86_64-linux-gnu/10/../../../../include/c++/10/cstdint"}},{"pid":1,"tid":0,"ph":"X","ts":153176,"dur":1269,"name":"ParseClass","args":{"detail":"std::char_traits"}},{"pid":1,"tid":0,"ph":"X","ts":154470,"dur":1321,"name":"ParseClass","args":{"detail":"std::char_traits"}},{"pid":1,"tid":0,"ph":"X","ts":116218,"dur":39591,"name":"Source","args":{"detail":"/usr/bin/../lib/gcc/x86_64-linux-gnu/10/../../../../include/c++/10/bits/char_traits.h"}},{"pid":1,"tid":0,"ph":"X","ts":155998,"dur":631,"name":"Source","args":{"detail":"/usr/include/locale.h"}},{"pid":1,"tid":0,"ph":"X","ts":155944,"dur":814,"name":"Source","args":{"detail":"/usr/bin/../lib/gcc/x86_64-linux-gnu/10/../../../../include/c++/10/clocale"}},{"pid":1,"tid":0,"ph":"X","ts":155908,"dur":1431,"name":"Source","args":{"detail":"/usr/bin/../lib/gcc/x86_64-linux-gnu/10/../../../../include/x86_64-linux-gnu/c++/10/bits/c++locale.h"}},{"pid":1,"tid":0,"ph":"X","ts":157438,"dur":1156,"name":"Source","args":{"detail":"/usr/include/ctype.h"}},{"pid":1,"tid":0,"ph":"X","ts":157383,"dur":1304,"name":"Source","args":{"detail":"/usr/bin/../lib/gcc/x86_64-linux-gnu/10/../../../../include/c++/10/cctype"}},{"pid":1,"tid":0,"ph":"X","ts":155855,"dur":3889,"name":"Source","args":{"detail":"/usr/bin/../lib/gcc/x86_64-linux-gnu/10/../../../../include/c++/10/bits/localefwd.h"}},{"pid":1,"tid":0,"ph":"X","ts":160072,"dur":1036,"name":"Source","args":{"detail":"/usr/include/sched.h"}},{"pid":1,"tid":0,"ph":"X","ts":161164,"dur":1876,"name":"Source","args":{"detail":"/usr/include/time.h"}},{"pid":1,"tid":0,"ph":"X","ts":160029,"dur":8723,"name":"Source","args":{"detail":"/usr/include/pthread.h"}},{"pid":1,"tid":0,"ph":"X","ts":159983,"dur":12223,"name":"Source","args":{"detail":"/usr/bin/../lib/gcc/x86_64-linux-gnu/10/../../../../include/x86_64-linux-gnu/c++/10/bits/gthr-default.h"}},{"pid":1,"tid":0,"ph":"X","ts":159920,"dur":12306,"name":"Source","args":{"detail":"/usr/bin/../lib/gcc/x86_64-linux-gnu/10/../../../../include/x86_64-linux-gnu/c++/10/bits/gthr.h"}},{"pid":1,"tid":0,"ph":"X","ts":159874,"dur":12936,"name":"Source","args":{"detail":"/usr/bin/../lib/gcc/x86_64-linux-gnu/10/../../../../include/c++/10/ext/atomicity.h"}},{"pid":1,"tid":0,"ph":"X","ts":173124,"dur":990,"name":"ParseClass","args":{"detail":"__gnu_cxx::new_allocator"}},{"pid":1,"tid":0,"ph":"X","ts":173029,"dur":1095,"name":"Source","args":{"detail":"/usr/bin/../lib/gcc/x86_64-linux-gnu/10/../../../../include/c++/10/ext/new_allocator.h"}},{"pid":1,"tid":0,"ph":"X","ts":173002,"dur":1170,"name":"Source","args":{"detail":"/usr/bin/../lib/gcc/x86_64-linux-gnu/10/../../../../include/x86_64-linux-gnu/c++/10/bits/c++allocator.h"}},{"pid":1,"tid":0,"ph":"X","ts":172973,"dur":3615,"name":"Source","args":{"detail":"/usr/bin/../lib/gcc/x86_64-linux-gnu/10/../../../../include/c++/10/bits/allocator.h"}},{"pid":1,"tid":0,"ph":"X","ts":176637,"dur":956,"name":"Source","args":{"detail":"/usr/bin/../lib/gcc/x86_64-linux-gnu/10/../../../../include/c++/10/bits/ostream_insert.h"}},{"pid":1,"tid":0,"ph":"X","ts":183696,"dur":665,"name":"Source","args":{"detail":"/usr/bin/../lib/gcc/x86_64-linux-gnu/10/../../../../include/c++/10/backward/binders.h"}},{"pid":1,"tid":0,"ph":"X","ts":177640,"dur":6724,"name":"Source","args":{"detail":"/usr/bin/../lib/gcc/x86_64-linux-gnu/10/../../../../include/c++/10/bits/stl_function.h"}},{"pid":1,"tid":0,"ph":"X","ts":185454,"dur":706,"name":"Source","args":{"detail":"/usr/bin/../lib/gcc/x86_64-linux-gnu/10/../../../../include/c++/10/bits/int_limits.h"}},{"pid":1,"tid":0,"ph":"X","ts":184411,"dur":2330,"name":"Source","args":{"detail":"/usr/bin/../lib/gcc/x86_64-linux-gnu/10/../../../../include/c++/10/bits/range_access.h"}},{"pid":1,"tid":0,"ph":"X","ts":187247,"dur":950,"name":"Source","args":{"detail":"/usr/bin/../lib/gcc/x86_64-linux-gnu/10/../../../../include/c++/10/bits/stl_construct.h"}},{"pid":1,"tid":0,"ph":"X","ts":188551,"dur":2189,"name":"ParseClass","args":{"detail":"std::allocator_traits"}},{"pid":1,"tid":0,"ph":"X","ts":190787,"dur":567,"name":"ParseClass","args":{"detail":"std::allocator_traits"}},{"pid":1,"tid":0,"ph":"X","ts":187219,"dur":6026,"name":"Source","args":{"detail":"/usr/bin/../lib/gcc/x86_64-linux-gnu/10/../../../../include/c++/10/bits/alloc_traits.h"}},{"pid":1,"tid":0,"ph":"X","ts":193325,"dur":1051,"name":"ParseClass","args":{"detail":"__gnu_cxx::__alloc_traits"}},{"pid":1,"tid":0,"ph":"X","ts":187178,"dur":7210,"name":"Source","args":{"detail":"/usr/bin/../lib/gcc/x86_64-linux-gnu/10/../../../../include/c++/10/ext/alloc_traits.h"}},{"pid":1,"tid":0,"ph":"X","ts":194481,"dur":10852,"name":"ParseClass","args":{"detail":"std::__cxx11::basic_string"}},{"pid":1,"tid":0,"ph":"X","ts":209295,"dur":671,"name":"Source","args":{"detail":"/usr/bin/../lib/gcc/x86_64-linux-gnu/10/../../../../include/c++/10/cstdlib"}},{"pid":1,"tid":0,"ph":"X","ts":210116,"dur":4434,"name":"Source","args":{"detail":"/usr/include/stdio.h"}},{"pid":1,"tid":0,"ph":"X","ts":210053,"dur":4740,"name":"Source","args":{"detail":"/usr/bin/../lib/gcc/x86_64-linux-gnu/10/../../../../include/c++/10/cstdio"}},{"pid":1,"tid":0,"ph":"X","ts":215365,"dur":640,"name":"ParseTemplate","args":{"detail":"__stoa"}},{"pid":1,"tid":0,"ph":"X","ts":209240,"dur":7040,"name":"Source","args":{"detail":"/usr/bin/../lib/gcc/x86_64-linux-gnu/10/../../../../include/c++/10/ext/string_conversions.h"}},{"pid":1,"tid":0,"ph":"X","ts":216314,"dur":683,"name":"Source","args":{"detail":"/usr/bin/../lib/gcc/x86_64-linux-gnu/10/../../../../include/c++/10/bits/charconv.h"}},{"pid":1,"tid":0,"ph":"X","ts":217126,"dur":2071,"name":"InstantiateClass","args":{"detail":"std::__cxx11::basic_string<char, std::char_traits<char>, std::allocator<char> >"}},{"pid":1,"tid":0,"ph":"X","ts":223773,"dur":541,"name":"InstantiateClass","args":{"detail":"__gnu_cxx::__alloc_traits<std::allocator<wchar_t>, wchar_t>"}},{"pid":1,"tid":0,"ph":"X","ts":223751,"dur":2074,"name":"InstantiateClass","args":{"detail":"std::__cxx11::basic_string<wchar_t, std::char_traits<wchar_t>, std::allocator<wchar_t> >"}},{"pid":1,"tid":0,"ph":"X","ts":228361,"dur":4088,"name":"Source","args":{"detail":"/usr/bin/../lib/gcc/x86_64-linux-gnu/10/../../../../include/c++/10/bits/functional_hash.h"}},{"pid":1,"tid":0,"ph":"X","ts":233229,"dur":2257,"name":"InstantiateClass","args":{"detail":"std::__cxx11::basic_string<char16_t, std::char_traits<char16_t>, std::allocator<char16_t> >"}},{"pid":1,"tid":0,"ph":"X","ts":233128,"dur":2439,"name":"ParseClass","args":{"detail":"std::hash"}},{"pid":1,"tid":0,"ph":"X","ts":235761,"dur":2225,"name":"InstantiateClass","args":{"detail":"std::__cxx11::basic_string<char32_t, std::char_traits<char32_t>, std::allocator<char32_t> >"}},{"pid":1,"tid":0,"ph":"X","ts":235649,"dur":2487,"name":"ParseClass","args":{"detail":"std::hash"}},{"pid":1,"tid":0,"ph":"X","ts":186782,"dur":51451,"name":"Source","args":{"detail":"/usr/bin/../lib/gcc/x86_64-linux-gnu/10/../../../../include/c++/10/bits/basic_string.h"}},{"pid":1,"tid":0,"ph":"X","ts":238299,"dur":9029,"name":"Source","args":{"detail":"/usr/bin/../lib/gcc/x86_64-linux-gnu/10/../../../../include/c++/10/bits/basic_string.tcc"}},{"pid":1,"tid":0,"ph":"X","ts":172925,"dur":74429,"name":"Source","args":{"detail":"/usr/bin/../lib/gcc/x86_64-linux-gnu/10/../../../../include/c++/10/string"}},{"pid":1,"tid":0,"ph":"X","ts":247418,"dur":1303,"name":"ParseClass","args":{"detail":"std::locale"}},{"pid":1,"tid":0,"ph":"X","ts":248740,"dur":619,"name":"ParseClass","args":{"detail":"std::locale::facet"}},{"pid":1,"tid":0,"ph":"X","ts":249596,"dur":1135,"name":"ParseClass","args":{"detail":"std::locale::_Impl"}},{"pid":1,"tid":0,"ph":"X","ts":250756,"dur":635,"name":"ParseClass","args":{"detail":"std::__cxx11::collate"}},{"pid":1,"tid":0,"ph":"X","ts":251489,"dur":670,"name":"InstantiateClass","args":{"detail":"std::__cxx11::collate<char>"}},{"pid":1,"tid":0,"ph":"X","ts":252867,"dur":2935,"name":"Source","args":{"detail":"/usr/bin/../lib/gcc/x86_64-linux-gnu/10/../../../../include/c++/10/bits/locale_classes.tcc"}},{"pid":1,"tid":0,"ph":"X","ts":172852,"dur":82953,"name":"Source","args":{"detail":"/usr/bin/../lib/gcc/x86_64-linux-gnu/10/../../../../include/c++/10/bits/locale_classes.h"}},{"pid":1,"tid":0,"ph":"X","ts":255930,"dur":579,"name":"Source","args":{"detail":"/usr/bin/../lib/gcc/x86_64-linux-gnu/10/../../../../include/x86_64-linux-gnu/c++/10/bits/error_constants.h"}},{"pid":1,"tid":0,"ph":"X","ts":256546,"dur":2370,"name":"Source","args":{"detail":"/usr/bin/../lib/gcc/x86_64-linux-gnu/10/../../../../include/c++/10/stdexcept"}},{"pid":1,"tid":0,"ph":"X","ts":259080,"dur":621,"name":"ParseClass","args":{"detail":"std::_V2::error_category"}},{"pid":1,"tid":0,"ph":"X","ts":259794,"dur":658,"name":"ParseClass","args":{"detail":"std::error_code"}},{"pid":1,"tid":0,"ph":"X","ts":261073,"dur":702,"name":"ParseClass","args":{"detail":"std::error_condition"}},{"pid":1,"tid":0,"ph":"X","ts":264044,"dur":1778,"name":"ParseClass","args":{"detail":"std::system_error"}},{"pid":1,"tid":0,"ph":"X","ts":255859,"dur":10528,"name":"Source","args":{"detail":"/usr/bin/../lib/gcc/x86_64-linux-gnu/10/../../../../include/c++/10/system_error"}},{"pid":1,"tid":0,"ph":"X","ts":270861,"dur":4129,"name":"ParseClass","args":{"detail":"std::ios_base"}},{"pid":1,"tid":0,"ph":"X","ts":159788,"dur":117044,"name":"Source","args":{"detail":"/usr/bin/../lib/gcc/x86_64-linux-gnu/10/../../../../include/c++/10/bits/ios_base.h"}},{"pid":1,"tid":0,"ph":"X","ts":277377,"dur":2939,"name":"ParseClass","args":{"detail":"std::basic_streambuf"}},{"pid":1,"tid":0,"ph":"X","ts":280683,"dur":2122,"name":"Source","args":{"detail":"/usr/bin/../lib/gcc/x86_64-linux-gnu/10/../../../../include/c++/10/bits/streambuf.tcc"}},{"pid":1,"tid":0,"ph":"X","ts":276898,"dur":5910,"name":"Source","args":{"detail":"/usr/bin/../lib/gcc/x86_64-linux-gnu/10/../../../../include/c++/10/streambuf"}},{"pid":1,"tid":0,"ph":"X","ts":283212,"dur":1473,"name":"Source","args":{"detail":"/usr/include/x86_64-linux-gnu/bits/wctype-wchar.h"}},{"pid":1,"tid":0,"ph":"X","ts":283148,"dur":2036,"name":"Source","args":{"detail":"/usr/include/wctype.h"}},{"pid":1,"tid":0,"ph":"X","ts":283076,"dur":2202,"name":"Source","args":{"detail":"/usr/bin/../lib/gcc/x86_64-linux-gnu/10/../../../../include/c++/10/cwctype"}},{"pid":1,"tid":0,"ph":"X","ts":285336,"dur":541,"name":"Source","args":{"detail":"/usr/bin/../lib/gcc/x86_64-linux-gnu/10/../../../../include/x86_64-linux-gnu/c++/10/bits/ctype_base.h"}},{"pid":1,"tid":0,"ph":"X","ts":286002,"dur":1231,"name":"ParseClass","args":{"detail":"std::istreambuf_iterator"}},{"pid":1,"tid":0,"ph":"X","ts":287465,"dur":595,"name":"ParseClass","args":{"detail":"std::ostreambuf_iterator"}},{"pid":1,"tid":0,"ph":"X","ts":285925,"dur":3595,"name":"Source","args":{"detail":"/usr/bin/../lib/gcc/x86_64-linux-gnu/10/../../../../include/c++/10/bits/streambuf_iterator.h"}},{"pid":1,"tid":0,"ph":"X","ts":290101,"dur":895,"name":"ParseClass","args":{"detail":"std::__ctype_abstract_base"}},{"pid":1,"tid":0,"ph":"X","ts":291535,"dur":2082,"name":"ParseClass","args":{"detail":"std::ctype"}},{"pid":1,"tid":0,"ph":"X","ts":293643,"dur":916,"name":"ParseClass","args":{"detail":"std::ctype"}},{"pid":1,"tid":0,"ph":"X","ts":295223,"dur":609,"name":"Source","args":{"detail":"/usr/bin/../lib/gcc/x86_64-linux-gnu/10/../../../../include/x86_64-linux-gnu/c++/10/bits/ctype_inline.h"}},{"pid":1,"tid":0,"ph":"X","ts":296550,"dur":712,"name":"ParseClass","args":{"detail":"std::__cxx11::numpunct"}},{"pid":1,"tid":0,"ph":"X","ts":298121,"dur":1881,"name":"ParseClass","args":{"detail":"std::num_get"}},{"pid":1,"tid":0,"ph":"X","ts":300077,"dur":990,"name":"ParseClass","args":{"detail":"std::num_put"}},{"pid":1,"tid":0,"ph":"X","ts":302673,"dur":1201,"name":"ParseTemplate","args":{"detail":"_M_cache"}},{"pid":1,"tid":0,"ph":"X","ts":305443,"dur":553,"name":"InstantiateClass","args":{"detail":"std::__or_<std::is_reference<std::allocator<char> >, std::is_function<std::allocator<char> >, std::is_void<std::allocator<char> >, std::__is_array_unknown_bounds<std::allocator<char> > >"}},{"pid":1,"tid":0,"ph":"X","ts":305203,"dur":998,"name":"InstantiateClass","args":{"detail":"std::is_nothrow_default_constructible<std::allocator<char> >"}},{"pid":1,"tid":0,"ph":"X","ts":304027,"dur":6918,"name":"ParseTemplate","args":{"detail":"_M_extract_float"}},{"pid":1,"tid":0,"ph":"X","ts":311034,"dur":3913,"name":"ParseTemplate","args":{"detail":"_M_extract_int"}},{"pid":1,"tid":0,"ph":"X","ts":315014,"dur":2394,"name":"ParseTemplate","args":{"detail":"do_get"}},{"pid":1,"tid":0,"ph":"X","ts":319271,"dur":501,"name":"ParseTemplate","args":{"detail":"__int_to_char"}},{"pid":1,"tid":0,"ph":"X","ts":319949,"dur":1571,"name":"ParseTemplate","args":{"detail":"_M_insert_int"}},{"pid":1,"tid":0,"ph":"X","ts":321782,"dur":1365,"name":"ParseTemplate","args":{"detail":"_M_insert_float"}},{"pid":1,"tid":0,"ph":"X","ts":323196,"dur":885,"name":"ParseTemplate","args":{"detail":"do_put"}},{"pid":1,"tid":0,"ph":"X","ts":324823,"dur":715,"name":"ParseTemplate","args":{"detail":"_S_pad"}},{"pid":1,"tid":0,"ph":"X","ts":302147,"dur":26024,"name":"Source","args":{"detail":"/usr/bin/../lib/gcc/x86_64-linux-gnu/10/../../../../include/c++/10/bits/locale_facets.tcc"}},{"pid":1,"tid":0,"ph":"X","ts":282920,"dur":45254,"name":"Source","args":{"detail":"/usr/bin/../lib/gcc/x86_64-linux-gnu/10/../../../../include/c++/10/bits/locale_facets.h"}},{"pid":1,"tid":0,"ph":"X","ts":328328,"dur":1819,"name":"ParseClass","args":{"detail":"std::basic_ios"}},{"pid":1,"tid":0,"ph":"X","ts":330216,"dur":1919,"name":"Source","args":{"detail":"/usr/bin/../lib/gcc/x86_64-linux-gnu/10/../../../../include/c++/10/bits/basic_ios.tcc"}},{"pid":1,"tid":0,"ph":"X","ts":282853,"dur":49286,"name":"Source","args":{"detail":"/usr/bin/../lib/gcc/x86_64-linux-gnu/10/../../../../include/c++/10/bits/basic_ios.h"}},{"pid":1,"tid":0,"ph":"X","ts":74857,"dur":257283,"name":"Source","args":{"detail":"/usr/bin/../lib/gcc/x86_64-linux-gnu/10/../../../../include/c++/10/ios"}},{"pid":1,"tid":0,"ph":"X","ts":332277,"dur":1334,"name":"ParseClass","args":{"detail":"std::basic_ostream"}},{"pid":1,"tid":0,"ph":"X","ts":337057,"dur":511,"name":"ParseTemplate","args":{"detail":"<unknown>"}},{"pid":1,"tid":0,"ph":"X","ts":335585,"dur":6288,"name":"Source","args":{"detail":"/usr/bin/../lib/gcc/x86_64-linux-gnu/10/../../../../include/c++/10/bits/ostream.tcc"}},{"pid":1,"tid":0,"ph":"X","ts":332182,"dur":9695,"name":"Source","args":{"detail":"/usr/bin/../lib/gcc/x86_64-linux-gnu/10/../../../../include/c++/10/ostream"}},{"pid":1,"tid":0,"ph":"X","ts":341924,"dur":1876,"name":"ParseClass","args":{"detail":"std::basic_istream"}},{"pid":1,"tid":0,"ph":"X","ts":347231,"dur":879,"name":"ParseTemplate","args":{"detail":"<unknown>"}},{"pid":1,"tid":0,"ph":"X","ts":348392,"dur":1154,"name":"ParseTemplate","args":{"detail":"<unknown>"}},{"pid":1,"tid":0,"ph":"X","ts":349589,"dur":751,"name":"ParseTemplate","args":{"detail":"<unknown>"}},{"pid":1,"tid":0,"ph":"X","ts":350383,"dur":724,"name":"ParseTemplate","args":{"detail":"<unknown>"}},{"pid":1,"tid":0,"ph":"X","ts":351149,"dur":553,"name":"ParseTemplate","args":{"detail":"get"}},{"pid":1,"tid":0,"ph":"X","ts":351746,"dur":547,"name":"ParseTemplate","args":{"detail":"get"}},{"pid":1,"tid":0,"ph":"X","ts":352344,"dur":691,"name":"ParseTemplate","args":{"detail":"get"}},{"pid":1,"tid":0,"ph":"X","ts":353082,"dur":632,"name":"ParseTemplate","args":{"detail":"get"}},{"pid":1,"tid":0,"ph":"X","ts":353766,"dur":879,"name":"ParseTemplate","args":{"detail":"getline"}},{"pid":1,"tid":0,"ph":"X","ts":355109,"dur":945,"name":"ParseTemplate","args":{"detail":"ignore"}},{"pid":1,"tid":0,"ph":"X","ts":356102,"dur":679,"name":"ParseTemplate","args":{"detail":"ignore"}},{"pid":1,"tid":0,"ph":"X","ts":360457,"dur":650,"name":"ParseTemplate","args":{"detail":"<unknown>"}},{"pid":1,"tid":0,"ph":"X","ts":361181,"dur":918,"name":"ParseTemplate","args":{"detail":"<unknown>"}},{"pid":1,"tid":0,"ph":"X","ts":362573,"dur":754,"name":"ParseTemplate","args":{"detail":"<unknown>"}},{"pid":1,"tid":0,"ph":"X","ts":364564,"dur":646,"name":"ParseTemplate","args":{"detail":"<unknown>"}},{"pid":1,"tid":0,"ph":"X","ts":347062,"dur":18736,"name":"Source","args":{"detail":"/usr/bin/../lib/gcc/x86_64-linux-gnu/10/../../../../include/c++/10/bits/istream.tcc"}},{"pid":1,"tid":0,"ph":"X","ts":74779,"dur":291023,"name":"Source","args":{"detail":"/usr/bin/../lib/gcc/x86_64-linux-gnu/10/../../../../include/c++/10/istream"}},{"pid":1,"tid":0,"ph":"X","ts":366049,"dur":683,"name":"ParseClass","args":{"detail":"std::__codecvt_abstract_base"}},{"pid":1,"tid":0,"ph":"X","ts":367290,"dur":664,"name":"ParseClass","args":{"detail":"std::codecvt"}},{"pid":1,"tid":0,"ph":"X","ts":367985,"dur":648,"name":"ParseClass","args":{"detail":"std::codecvt"}},{"pid":1,"tid":0,"ph":"X","ts":368666,"dur":658,"name":"ParseClass","args":{"detail":"std::codecvt"}},{"pid":1,"tid":0,"ph":"X","ts":369351,"dur":602,"name":"ParseClass","args":{"detail":"std::codecvt"}},{"pid":1,"tid":0,"ph":"X","ts":365877,"dur":5485,"name":"Source","args":{"detail":"/usr/bin/../lib/gcc/x86_64-linux-gnu/10/../../../../include/c++/10/bits/codecvt.h"}},{"pid":1,"tid":0,"ph":"X","ts":373104,"dur":510,"name":"InstantiateClass","args":{"detail":"std::__or_<std::is_reference<_IO_FILE *>, std::is_function<_IO_FILE *>, std::is_void<_IO_FILE *>, std::__is_array_unknown_bounds<_IO_FILE *> >"}},{"pid":1,"tid":0,"ph":"X","ts":372900,"dur":883,"name":"InstantiateClass","args":{"detail":"std::is_move_constructible<_IO_FILE *>"}},{"pid":1,"tid":0,"ph":"X","ts":372894,"dur":1098,"name":"InstantiateClass","args":{"detail":"std::__and_<std::is_move_constructible<_IO_FILE *>, std::is_move_assignable<_IO_FILE *> >"}},{"pid":1,"tid":0,"ph":"X","ts":372606,"dur":1391,"name":"InstantiateClass","args":{"detail":"std::__and_<std::__not_<std::__is_tuple_like<_IO_FILE *> >, std::is_move_constructible<_IO_FILE *>, std::is_move_assignable<_IO_FILE *> >"}},{"pid":1,"tid":0,"ph":"X","ts":374066,"dur":714,"name":"InstantiateClass","args":{"detail":"std::__and_<std::is_nothrow_move_constructible<_IO_FILE *>, std::is_nothrow_move_assignable<_IO_FILE *> >"}},{"pid":1,"tid":0,"ph":"X","ts":375033,"dur":779,"name":"InstantiateClass","args":{"detail":"std::is_move_constructible<bool>"}},{"pid":1,"tid":0,"ph":"X","ts":375027,"dur":991,"name":"InstantiateClass","args":{"detail":"std::__and_<std::is_move_constructible<bool>, std::is_move_assignable<bool> >"}},{"pid":1,"tid":0,"ph":"X","ts":374871,"dur":1152,"name":"InstantiateClass","args":{"detail":"std::__and_<std::__not_<std::__is_tuple_like<bool> >, std::is_move_constructible<bool>, std::is_move_assignable<bool> >"}},{"pid":1,"tid":0,"ph":"X","ts":376088,"dur":705,"name":"InstantiateClass","args":{"detail":"std::__and_<std::is_nothrow_move_constructible<bool>, std::is_nothrow_move_assignable<bool> >"}},{"pid":1,"tid":0,"ph":"X","ts":371783,"dur":5058,"name":"ParseClass","args":{"detail":"std::__basic_file"}},{"pid":1,"tid":0,"ph":"X","ts":371450,"dur":5402,"name":"Source","args":{"detail":"/usr/bin/../lib/gcc/x86_64-linux-gnu/10/../../../../include/x86_64-linux-gnu/c++/10/bits/basic_file.h"}},{"pid":1,"tid":0,"ph":"X","ts":376931,"dur":1897,"name":"ParseClass","args":{"detail":"std::basic_filebuf"}},{"pid":1,"tid":0,"ph":"X","ts":378866,"dur":1040,"name":"ParseClass","args":{"detail":"std::basic_ifstream"}},{"pid":1,"tid":0,"ph":"X","ts":379929,"dur":1041,"name":"ParseClass","args":{"detail":"std::basic_ofstream"}},{"pid":1,"tid":0,"ph":"X","ts":380992,"dur":1192,"name":"ParseClass","args":{"detail":"std::basic_fstream"}},{"pid":1,"tid":0,"ph":"X","ts":384224,"dur":569,"name":"ParseTemplate","args":{"detail":"open"}},{"pid":1,"tid":0,"ph":"X","ts":385431,"dur":1846,"name":"ParseTemplate","args":{"detail":"underflow"}},{"pid":1,"tid":0,"ph":"X","ts":388293,"dur":1138,"name":"ParseTemplate","args":{"detail":"_M_convert_to_external"}},{"pid":1,"tid":0,"ph":"X","ts":389475,"dur":634,"name":"ParseTemplate","args":{"detail":"xsgetn"}},{"pid":1,"tid":0,"ph":"X","ts":390153,"dur":538,"name":"ParseTemplate","args":{"detail":"xsputn"}},{"pid":1,"tid":0,"ph":"X","ts":390900,"dur":580,"name":"ParseTemplate","args":{"detail":"seekoff"}},{"pid":1,"tid":0,"ph":"X","ts":391974,"dur":916,"name":"ParseTemplate","args":{"detail":"_M_terminate_output"}},{"pid":1,"tid":0,"ph":"X","ts":393852,"dur":505,"name":"InstantiateClass","args":{"detail":"std::__or_<std::is_reference<__mbstate_t>, std::is_function<__mbstate_t>, std::is_void<__mbstate_t>, std::__is_array_unknown_bounds<__mbstate_t> >"}},{"pid":1,"tid":0,"ph":"X","ts":393565,"dur":943,"name":"InstantiateClass","args":{"detail":"std::is_copy_assignable<__mbstate_t>"}},{"pid":1,"tid":0,"ph":"X","ts":394653,"dur":528,"name":"InstantiateClass","args":{"detail":"std::__and_<std::is_copy_constructible<__mbstate_t>, std::is_default_constructible<__mbstate_t> >"}},{"pid":1,"tid":0,"ph":"X","ts":393556,"dur":1630,"name":"InstantiateClass","args":{"detail":"std::__and_<std::is_copy_assignable<__mbstate_t>, std::is_copy_constructible<__mbstate_t>, std::is_default_constructible<__mbstate_t> >"}},{"pid":1,"tid":0,"ph":"X","ts":393476,"dur":2029,"name":"InstantiateClass","args":{"detail":"std::basic_filebuf<char, std::char_traits<char> >"}},{"pid":1,"tid":0,"ph":"X","ts":382595,"dur":14297,"name":"Source","args":{"detail":"/usr/bin/../lib/gcc/x86_64-linux-gnu/10/../../../../include/c++/10/bits/fstream.tcc"}},{"pid":1,"tid":0,"ph":"X","ts":74682,"dur":322225,"name":"Source","args":{"detail":"/usr/bin/../lib/gcc/x86_64-linux-gnu/10/../../../../include/c++/10/fstream"}},{"pid":1,"tid":0,"ph":"X","ts":398033,"dur":565,"name":"InstantiateClass","args":{"detail":"std::__is_convertible_to_basic_ostream<std::basic_ofstream<char> &>"}},{"pid":1,"tid":0,"ph":"X","ts":400833,"dur":1911,"name":"CodeGen Function","args":{"detail":"main"}},{"pid":1,"tid":0,"ph":"X","ts":402895,"dur":754,"name":"InstantiateFunction","args":{"detail":"__gnu_cxx::__stoa<long, int, char, int>"}},{"pid":1,"tid":0,"ph":"X","ts":403651,"dur":735,"name":"InstantiateFunction","args":{"detail":"__gnu_cxx::__stoa<long, long, char, int>"}},{"pid":1,"tid":0,"ph":"X","ts":404388,"dur":625,"name":"InstantiateFunction","args":{"detail":"__gnu_cxx::__stoa<unsigned long, unsigned long, char, int>"}},{"pid":1,"tid":0,"ph":"X","ts":405014,"dur":610,"name":"InstantiateFunction","args":{"detail":"__gnu_cxx::__stoa<long long, long long, char, int>"}},{"pid":1,"tid":0,"ph":"X","ts":405625,"dur":620,"name":"InstantiateFunction","args":{"detail":"__gnu_cxx::__stoa<unsigned long long, unsigned long long, char, int>"}},{"pid":1,"tid":0,"ph":"X","ts":406247,"dur":613,"name":"InstantiateFunction","args":{"detail":"__gnu_cxx::__stoa<float, float, char>"}},{"pid":1,"tid":0,"ph":"X","ts":406861,"dur":625,"name":"InstantiateFunction","args":{"detail":"__gnu_cxx::__stoa<double, double, char>"}},{"pid":1,"tid":0,"ph":"X","ts":407487,"dur":617,"name":"InstantiateFunction","args":{"detail":"__gnu_cxx::__stoa<long double, long double, char>"}},{"pid":1,"tid":0,"ph":"X","ts":408106,"dur":515,"name":"InstantiateFunction","args":{"detail":"std::__detail::__to_chars_len<unsigned int>"}},{"pid":1,"tid":0,"ph":"X","ts":408722,"dur":674,"name":"InstantiateFunction","args":{"detail":"std::__cxx11::basic_string<char, std::char_traits<char>, std::allocator<char> >::basic_string"}},{"pid":1,"tid":0,"ph":"X","ts":409439,"dur":667,"name":"InstantiateFunction","args":{"detail":"std::__cxx11::basic_string<char, std::char_traits<char>, std::allocator<char> >::_M_dispose"}},{"pid":1,"tid":0,"ph":"X","ts":409397,"dur":709,"name":"InstantiateFunction","args":{"detail":"std::__cxx11::basic_string<char, std::char_traits<char>, std::allocator<char> >::~basic_string"}},{"pid":1,"tid":0,"ph":"X","ts":410442,"dur":789,"name":"InstantiateFunction","args":{"detail":"std::__cxx11::basic_string<char, std::char_traits<char>, std::allocator<char> >::basic_string"}},{"pid":1,"tid":0,"ph":"X","ts":411263,"dur":536,"name":"InstantiateFunction","args":{"detail":"std::__detail::__to_chars_len<unsigned long>"}},{"pid":1,"tid":0,"ph":"X","ts":412085,"dur":578,"name":"InstantiateFunction","args":{"detail":"std::__detail::__to_chars_len<unsigned long long>"}},{"pid":1,"tid":0,"ph":"X","ts":413157,"dur":557,"name":"InstantiateClass","args":{"detail":"std::is_convertible<std::random_access_iterator_tag, std::input_iterator_tag>"}},{"pid":1,"tid":0,"ph":"X","ts":414346,"dur":1265,"name":"InstantiateFunction","args":{"detail":"std::__cxx11::basic_string<char, std::char_traits<char>, std::allocator<char> >::_M_construct<char *>"}},{"pid":1,"tid":0,"ph":"X","ts":414118,"dur":1493,"name":"InstantiateFunction","args":{"detail":"std::__cxx11::basic_string<char, std::char_traits<char>, std::allocator<char> >::_M_construct_aux<char *>"}},{"pid":1,"tid":0,"ph":"X","ts":413965,"dur":1647,"name":"InstantiateFunction","args":{"detail":"std::__cxx11::basic_string<char, std::char_traits<char>, std::allocator<char> >::_M_construct<char *>"}},{"pid":1,"tid":0,"ph":"X","ts":413847,"dur":1765,"name":"InstantiateFunction","args":{"detail":"std::__cxx11::basic_string<char, std::char_traits<char>, std::allocator<char> >::basic_string<char *, void>"}},{"pid":1,"tid":0,"ph":"X","ts":412956,"dur":2657,"name":"InstantiateFunction","args":{"detail":"__gnu_cxx::__to_xstring<std::__cxx11::basic_string<char>, char>"}},{"pid":1,"tid":0,"ph":"X","ts":415714,"dur":593,"name":"InstantiateFunction","args":{"detail":"__gnu_cxx::__stoa<long, int, wchar_t, int>"}},{"pid":1,"tid":0,"ph":"X","ts":416309,"dur":527,"name":"InstantiateFunction","args":{"detail":"__gnu_cxx::__stoa<long, long, wchar_t, int>"}},{"pid":1,"tid":0,"ph":"X","ts":416838,"dur":526,"name":"InstantiateFunction","args":{"detail":"__gnu_cxx::__stoa<unsigned long, unsigned long, wchar_t, int>"}},{"pid":1,"tid":0,"ph":"X","ts":417366,"dur":527,"name":"InstantiateFunction","args":{"detail":"__gnu_cxx::__stoa<long long, long long, wchar_t, int>"}},{"pid":1,"tid":0,"ph":"X","ts":417895,"dur":527,"name":"InstantiateFunction","args":{"detail":"__gnu_cxx::__stoa<unsigned long long, unsigned long long, wchar_t, int>"}},{"pid":1,"tid":0,"ph":"X","ts":418423,"dur":543,"name":"InstantiateFunction","args":{"detail":"__gnu_cxx::__stoa<float, float, wchar_t>"}},{"pid":1,"tid":0,"ph":"X","ts":418967,"dur":732,"name":"InstantiateFunction","args":{"detail":"__gnu_cxx::__stoa<double, double, wchar_t>"}},{"pid":1,"tid":0,"ph":"X","ts":419701,"dur":584,"name":"InstantiateFunction","args":{"detail":"__gnu_cxx::__stoa<long double, long double, wchar_t>"}},{"pid":1,"tid":0,"ph":"X","ts":423034,"dur":780,"name":"InstantiateFunction","args":{"detail":"std::__cxx11::basic_string<wchar_t, std::char_traits<wchar_t>, std::allocator<wchar_t> >::_M_dispose"}},{"pid":1,"tid":0,"ph":"X","ts":421712,"dur":2223,"name":"InstantiateFunction","args":{"detail":"std::__cxx11::basic_string<wchar_t, std::char_traits<wchar_t>, std::allocator<wchar_t> >::_M_construct<wchar_t *>"}},{"pid":1,"tid":0,"ph":"X","ts":421585,"dur":2351,"name":"InstantiateFunction","args":{"detail":"std::__cxx11::basic_string<wchar_t, std::char_traits<wchar_t>, std::allocator<wchar_t> >::_M_construct_aux<wchar_t *>"}},{"pid":1,"tid":0,"ph":"X","ts":421453,"dur":2484,"name":"InstantiateFunction","args":{"detail":"std::__cxx11::basic_string<wchar_t, std::char_traits<wchar_t>, std::allocator<wchar_t> >::_M_construct<wchar_t *>"}},{"pid":1,"tid":0,"ph":"X","ts":420737,"dur":3200,"name":"InstantiateFunction","args":{"detail":"std::__cxx11::basic_string<wchar_t, std::char_traits<wchar_t>, std::allocator<wchar_t> >::basic_string<wchar_t *, void>"}},{"pid":1,"tid":0,"ph":"X","ts":423982,"dur":582,"name":"InstantiateFunction","args":{"detail":"std::__cxx11::basic_string<wchar_t, std::char_traits<wchar_t>, std::allocator<wchar_t> >::basic_string"}},{"pid":1,"tid":0,"ph":"X","ts":420287,"dur":4278,"name":"InstantiateFunction","args":{"detail":"__gnu_cxx::__to_xstring<std::__cxx11::basic_string<wchar_t>, wchar_t>"}},{"pid":1,"tid":0,"ph":"X","ts":425019,"dur":832,"name":"InstantiateFunction","args":{"detail":"std::operator+<char, std::char_traits<char>, std::allocator<char> >"}},{"pid":1,"tid":0,"ph":"X","ts":425852,"dur":1270,"name":"InstantiateFunction","args":{"detail":"std::operator+<char, std::char_traits<char>, std::allocator<char> >"}},{"pid":1,"tid":0,"ph":"X","ts":428054,"dur":724,"name":"InstantiateFunction","args":{"detail":"std::basic_ofstream<char, std::char_traits<char> >::basic_ofstream"}},{"pid":1,"tid":0,"ph":"X","ts":402776,"dur":26539,"name":"PerformPendingInstantiations"},{"pid":1,"tid":0,"ph":"X","ts":1384,"dur":427970,"name":"Frontend"},{"pid":1,"tid":0,"ph":"X","ts":429991,"dur":4958,"name":"OptModule","args":{"detail":"/home/daveb/C++/cmake_tutorial/MathFunctions/MakeTable.cxx"}},{"pid":1,"tid":0,"ph":"X","ts":429987,"dur":4963,"name":"PerModulePasses"},{"pid":1,"tid":0,"ph":"X","ts":429645,"dur":5381,"name":"Backend"},{"pid":1,"tid":0,"ph":"X","ts":35,"dur":435377,"name":"ExecuteCompiler"},{"pid":1,"tid":1,"ph":"X","ts":0,"dur":435377,"name":"Total ExecuteCompiler","args":{"count":1,"avg ms":435}},{"pid":1,"tid":2,"ph":"X","ts":0,"dur":428250,"name":"Total Frontend","args":{"count":2,"avg ms":214}},{"pid":1,"tid":3,"ph":"X","ts":0,"dur":395238,"name":"Total Source","args":{"count":3,"avg ms":131}},{"pid":1,"tid":4,"ph":"X","ts":0,"dur":125662,"name":"Total ParseClass","args":{"count":733,"avg ms":0}},{"pid":1,"tid":5,"ph":"X","ts":0,"dur":86285,"name":"Total ParseTemplate","args":{"count":717,"avg ms":0}},{"pid":1,"tid":6,"ph":"X","ts":0,"dur":35992,"name":"Total InstantiateClass","args":{"count":197,"avg ms":0}},{"pid":1,"tid":7,"ph":"X","ts":0,"dur":26657,"name":"Total InstantiateFunction","args":{"count":66,"avg ms":0}},{"pid":1,"tid":8,"ph":"X","ts":0,"dur":26539,"name":"Total PerformPendingInstantiations","args":{"count":1,"avg ms":26}},{"pid":1,"tid":9,"ph":"X","ts":0,"dur":5381,"name":"Total Backend","args":{"count":1,"avg ms":5}},{"pid":1,"tid":10,"ph":"X","ts":0,"dur":4963,"name":"Total PerModulePasses","args":{"count":1,"avg ms":4}},{"pid":1,"tid":11,"ph":"X","ts":0,"dur":4958,"name":"Total OptModule","args":{"count":2,"avg ms":2}},{"pid":1,"tid":12,"ph":"X","ts":0,"dur":1911,"name":"Total CodeGen Function","args":{"count":1,"avg ms":1}},{"pid":1,"tid":13,"ph":"X","ts":0,"dur":1083,"name":"Total OptFunction","args":{"count":17,"avg ms":0}},{"pid":1,"tid":14,"ph":"X","ts":0,"dur":1067,"name":"Total RunPass","args":{"count":41,"avg ms":0}},{"pid":1,"tid":15,"ph":"X","ts":0,"dur":29,"name":"Total PerFunctionPasses","args":{"count":1,"avg ms":0}},{"pid":1,"tid":16,"ph":"X","ts":0,"dur":1,"name":"Total CodeGenPasses","args":{"count":1,"avg ms":0}},{"cat":"","pid":1,"tid":0,"ts":0,"ph":"M","name":"process_name","args":{"name":"clang"}}]}